{
  "nodes": [
    {
      "id": "1356733765544992769",
      "url": "https://twitter.com/theyluv_nia/status/1356733765544992769",
      "user": "theyluv_nia",
      "text": "Valentine\u2019s is coming, where\u2019s your boyfriend?\\n\\nGet your boo a gift with the help of my gift guide, black brand edition\ud83c\udf39https://t.co/0o608prFYs \\n#shopblack https://t.co/GWWRey7XjU",
      "sentiment": 0.8176
    },
    {
      "id": "1356733982663192580",
      "url": "https://twitter.com/theyluv_nia/status/1356733982663192580",
      "user": "theyluv_nia",
      "text": "@fentybeauty on the lips per usual",
      "sentiment": 0.0
    }
  ],
  "edges": [
    [
      "1356733982663192580",
      "1356733765544992769"
    ]
  ]
}