{
  "nodes": [
    {
      "id": "1395518032785526787",
      "url": "https://twitter.com/breeny122/1395518032785526787",
      "user": "breeny122",
      "sentiment": 0.5411
    },
    {
      "id": "1395519706912657408",
      "url": "https://twitter.com/KwikWarren/1395519706912657408",
      "user": "KwikWarren",
      "sentiment": 0.4404
    },
    {
      "id": "1395392514794872836",
      "url": "https://twitter.com/KwikWarren/1395392514794872836",
      "user": "KwikWarren",
      "sentiment": 0.0
    },
    {
      "id": "1395391370274037769",
      "url": "https://twitter.com/breeny122/1395391370274037769",
      "user": "breeny122",
      "sentiment": 0.2003
    },
    {
      "id": "1394620329662746627",
      "url": "https://twitter.com/KwikWarren/1394620329662746627",
      "user": "KwikWarren",
      "sentiment": -0.7123
    },
    {
      "id": "1395320788501233671",
      "url": "https://twitter.com/Mystiwoman/1395320788501233671",
      "user": "Mystiwoman",
      "sentiment": 0.4912
    },
    {
      "id": "1395379083983265810",
      "url": "https://twitter.com/MarnaDua4/1395379083983265810",
      "user": "MarnaDua4",
      "sentiment": -0.9325
    },
    {
      "id": "1395317929319694340",
      "url": "https://twitter.com/Mystiwoman/1395317929319694340",
      "user": "Mystiwoman",
      "sentiment": -0.5714
    },
    {
      "id": "1395340270321950722",
      "url": "https://twitter.com/KwikWarren/1395340270321950722",
      "user": "KwikWarren",
      "sentiment": -0.2516
    },
    {
      "id": "1395318649737539590",
      "url": "https://twitter.com/Mystiwoman/1395318649737539590",
      "user": "Mystiwoman",
      "sentiment": 0.1253
    },
    {
      "id": "1395340130077052928",
      "url": "https://twitter.com/KwikWarren/1395340130077052928",
      "user": "KwikWarren",
      "sentiment": 0.4404
    },
    {
      "id": "1395340026754609152",
      "url": "https://twitter.com/KwikWarren/1395340026754609152",
      "user": "KwikWarren",
      "sentiment": 0.296
    },
    {
      "id": "1394645905706467334",
      "url": "https://twitter.com/KwikWarren/1394645905706467334",
      "user": "KwikWarren",
      "sentiment": 0.1901
    },
    {
      "id": "1394645598322659331",
      "url": "https://twitter.com/MarnaDua4/1394645598322659331",
      "user": "MarnaDua4",
      "sentiment": -0.25
    },
    {
      "id": "1395319131084189696",
      "url": "https://twitter.com/Mystiwoman/1395319131084189696",
      "user": "Mystiwoman",
      "sentiment": 0.128
    },
    {
      "id": "1394653253061816322",
      "url": "https://twitter.com/KwikWarren/1394653253061816322",
      "user": "KwikWarren",
      "sentiment": 0.0
    },
    {
      "id": "1395017988345110528",
      "url": "https://twitter.com/4thViv/1395017988345110528",
      "user": "4thViv",
      "sentiment": 0.8687
    },
    {
      "id": "1394976748891250689",
      "url": "https://twitter.com/mkelleynsb/1394976748891250689",
      "user": "mkelleynsb",
      "sentiment": -0.1027
    },
    {
      "id": "1394978243078393857",
      "url": "https://twitter.com/flea_flicka/1394978243078393857",
      "user": "flea_flicka",
      "sentiment": 0.0
    },
    {
      "id": "1394814086681088001",
      "url": "https://twitter.com/flea_flicka/1394814086681088001",
      "user": "flea_flicka",
      "sentiment": 0.3987
    },
    {
      "id": "1394970668651921410",
      "url": "https://twitter.com/mickey07727429/1394970668651921410",
      "user": "mickey07727429",
      "sentiment": 0.0387
    },
    {
      "id": "1394971183423053826",
      "url": "https://twitter.com/KwikWarren/1394971183423053826",
      "user": "KwikWarren",
      "sentiment": 0.0
    },
    {
      "id": "1394969686123630595",
      "url": "https://twitter.com/CARTER61811828/1394969686123630595",
      "user": "CARTER61811828",
      "sentiment": -0.965
    },
    {
      "id": "1394666356482600963",
      "url": "https://twitter.com/52Katydid/1394666356482600963",
      "user": "52Katydid",
      "sentiment": 0.25
    },
    {
      "id": "1394946481635971074",
      "url": "https://twitter.com/crc7761/1394946481635971074",
      "user": "crc7761",
      "sentiment": 0.0
    },
    {
      "id": "1394946252958281731",
      "url": "https://twitter.com/crc7761/1394946252958281731",
      "user": "crc7761",
      "sentiment": 0.1877
    },
    {
      "id": "1394937075754049537",
      "url": "https://twitter.com/cheval_blanc/1394937075754049537",
      "user": "cheval_blanc",
      "sentiment": -0.5106
    },
    {
      "id": "1394879730940358659",
      "url": "https://twitter.com/langlinais_toni/1394879730940358659",
      "user": "langlinais_toni",
      "sentiment": 0.0
    },
    {
      "id": "1394846439075942401",
      "url": "https://twitter.com/nancychando26/1394846439075942401",
      "user": "nancychando26",
      "sentiment": 0.0
    },
    {
      "id": "1394832399486398465",
      "url": "https://twitter.com/Nancy63161899/1394832399486398465",
      "user": "Nancy63161899",
      "sentiment": -0.4767
    },
    {
      "id": "1394837186143473674",
      "url": "https://twitter.com/eleanor2600/1394837186143473674",
      "user": "eleanor2600",
      "sentiment": 0.7579
    },
    {
      "id": "1394832600473165825",
      "url": "https://twitter.com/UnRapporteur1/1394832600473165825",
      "user": "UnRapporteur1",
      "sentiment": 0.6597
    },
    {
      "id": "1394833740065542150",
      "url": "https://twitter.com/Nancy63161899/1394833740065542150",
      "user": "Nancy63161899",
      "sentiment": -0.3182
    },
    {
      "id": "1394624048496271366",
      "url": "https://twitter.com/mkelleynsb/1394624048496271366",
      "user": "mkelleynsb",
      "sentiment": 0.6486
    },
    {
      "id": "1394833494132596741",
      "url": "https://twitter.com/Nancy63161899/1394833494132596741",
      "user": "Nancy63161899",
      "sentiment": 0.09
    },
    {
      "id": "1394660122740150274",
      "url": "https://twitter.com/hippyniki/1394660122740150274",
      "user": "hippyniki",
      "sentiment": -0.4005
    },
    {
      "id": "1394652776584654851",
      "url": "https://twitter.com/eleanor2600/1394652776584654851",
      "user": "eleanor2600",
      "sentiment": -0.631
    },
    {
      "id": "1394821115403333633",
      "url": "https://twitter.com/KDawn___/1394821115403333633",
      "user": "KDawn___",
      "sentiment": 0.8655
    },
    {
      "id": "1394819494896312320",
      "url": "https://twitter.com/MicheleCr01/1394819494896312320",
      "user": "MicheleCr01",
      "sentiment": 0.0
    },
    {
      "id": "1394820381979123716",
      "url": "https://twitter.com/KwikWarren/1394820381979123716",
      "user": "KwikWarren",
      "sentiment": 0.0
    },
    {
      "id": "1394819948141158403",
      "url": "https://twitter.com/MicheleCr01/1394819948141158403",
      "user": "MicheleCr01",
      "sentiment": 0.4215
    },
    {
      "id": "1394620663739133956",
      "url": "https://twitter.com/timothy_staab/1394620663739133956",
      "user": "timothy_staab",
      "sentiment": 0.3182
    },
    {
      "id": "1394815299212484609",
      "url": "https://twitter.com/AirspaceGeek/1394815299212484609",
      "user": "AirspaceGeek",
      "sentiment": -0.574
    },
    {
      "id": "1394769708008751104",
      "url": "https://twitter.com/cheval_blanc/1394769708008751104",
      "user": "cheval_blanc",
      "sentiment": -0.8641
    },
    {
      "id": "1394810567974662145",
      "url": "https://twitter.com/hindman_e/1394810567974662145",
      "user": "hindman_e",
      "sentiment": 0.3612
    },
    {
      "id": "1394809747270897669",
      "url": "https://twitter.com/healingnstyle/1394809747270897669",
      "user": "healingnstyle",
      "sentiment": -0.2203
    },
    {
      "id": "1394804878661193732",
      "url": "https://twitter.com/KcKeyboardist/1394804878661193732",
      "user": "KcKeyboardist",
      "sentiment": -0.2023
    },
    {
      "id": "1394802895799865348",
      "url": "https://twitter.com/sittinonthebaby/1394802895799865348",
      "user": "sittinonthebaby",
      "sentiment": 0.0
    },
    {
      "id": "1394798888851316742",
      "url": "https://twitter.com/Kamper64385709/1394798888851316742",
      "user": "Kamper64385709",
      "sentiment": -0.4019
    },
    {
      "id": "1394794882137567234",
      "url": "https://twitter.com/LisaFlo37159238/1394794882137567234",
      "user": "LisaFlo37159238",
      "sentiment": 0.128
    },
    {
      "id": "1394795086974787587",
      "url": "https://twitter.com/LisaFlo37159238/1394795086974787587",
      "user": "LisaFlo37159238",
      "sentiment": 0.0
    },
    {
      "id": "1394784394150285315",
      "url": "https://twitter.com/BldheartLib/1394784394150285315",
      "user": "BldheartLib",
      "sentiment": 0.6249
    },
    {
      "id": "1394794736297336838",
      "url": "https://twitter.com/nellygiannini/1394794736297336838",
      "user": "nellygiannini",
      "sentiment": 0.7184
    },
    {
      "id": "1394793456397127681",
      "url": "https://twitter.com/tina_martens/1394793456397127681",
      "user": "tina_martens",
      "sentiment": 0.0
    },
    {
      "id": "1394792948722765827",
      "url": "https://twitter.com/Leopoldtweets/1394792948722765827",
      "user": "Leopoldtweets",
      "sentiment": 0.0
    },
    {
      "id": "1394789176730525697",
      "url": "https://twitter.com/JWWareWolf75/1394789176730525697",
      "user": "JWWareWolf75",
      "sentiment": 0.0
    },
    {
      "id": "1394789031385436165",
      "url": "https://twitter.com/HawkeyeUofIA/1394789031385436165",
      "user": "HawkeyeUofIA",
      "sentiment": -0.4417
    },
    {
      "id": "1394663559318081538",
      "url": "https://twitter.com/pricklyeater/1394663559318081538",
      "user": "pricklyeater",
      "sentiment": 0.6906
    },
    {
      "id": "1394788444220665867",
      "url": "https://twitter.com/BooksRule54/1394788444220665867",
      "user": "BooksRule54",
      "sentiment": 0.0
    },
    {
      "id": "1394769126141403146",
      "url": "https://twitter.com/PatGill13854679/1394769126141403146",
      "user": "PatGill13854679",
      "sentiment": -0.8043
    },
    {
      "id": "1394761900504666113",
      "url": "https://twitter.com/Jmonte41739837/1394761900504666113",
      "user": "Jmonte41739837",
      "sentiment": 0.0
    },
    {
      "id": "1394756995589283845",
      "url": "https://twitter.com/bellefountain/1394756995589283845",
      "user": "bellefountain",
      "sentiment": 0.0
    },
    {
      "id": "1394756925909176321",
      "url": "https://twitter.com/piamanning3/1394756925909176321",
      "user": "piamanning3",
      "sentiment": 0.0
    },
    {
      "id": "1394750725364740097",
      "url": "https://twitter.com/CathyJBrown1/1394750725364740097",
      "user": "CathyJBrown1",
      "sentiment": -0.4404
    },
    {
      "id": "1394755979594633219",
      "url": "https://twitter.com/xmagicmomentsx/1394755979594633219",
      "user": "xmagicmomentsx",
      "sentiment": 0.0
    },
    {
      "id": "1394755487921590274",
      "url": "https://twitter.com/NoArgumentHere/1394755487921590274",
      "user": "NoArgumentHere",
      "sentiment": -0.6801
    },
    {
      "id": "1394747900358389766",
      "url": "https://twitter.com/BlueOc1981/1394747900358389766",
      "user": "BlueOc1981",
      "sentiment": 0.5095
    },
    {
      "id": "1394751743058079747",
      "url": "https://twitter.com/OWLSI1/1394751743058079747",
      "user": "OWLSI1",
      "sentiment": 0.9312
    },
    {
      "id": "1394750666380390403",
      "url": "https://twitter.com/WendyBl22142187/1394750666380390403",
      "user": "WendyBl22142187",
      "sentiment": 0.0
    },
    {
      "id": "1394749932100259844",
      "url": "https://twitter.com/Hoover5454/1394749932100259844",
      "user": "Hoover5454",
      "sentiment": 0.0
    },
    {
      "id": "1394749436882915328",
      "url": "https://twitter.com/SideeyeSlant/1394749436882915328",
      "user": "SideeyeSlant",
      "sentiment": -0.5771
    },
    {
      "id": "1394749239201312777",
      "url": "https://twitter.com/Mjcrjdrvrsoonrf/1394749239201312777",
      "user": "Mjcrjdrvrsoonrf",
      "sentiment": -0.6908
    },
    {
      "id": "1394749369832902668",
      "url": "https://twitter.com/JohnKaminar/1394749369832902668",
      "user": "JohnKaminar",
      "sentiment": -0.4926
    },
    {
      "id": "1394749328804175877",
      "url": "https://twitter.com/JaneEnygma57/1394749328804175877",
      "user": "JaneEnygma57",
      "sentiment": -0.6532
    },
    {
      "id": "1394748802100236295",
      "url": "https://twitter.com/JohnKaminar/1394748802100236295",
      "user": "JohnKaminar",
      "sentiment": 0.0
    },
    {
      "id": "1394748081174990854",
      "url": "https://twitter.com/Mjcrjdrvrsoonrf/1394748081174990854",
      "user": "Mjcrjdrvrsoonrf",
      "sentiment": 0.0
    },
    {
      "id": "1394747032070344705",
      "url": "https://twitter.com/OWLSI1/1394747032070344705",
      "user": "OWLSI1",
      "sentiment": 0.0
    },
    {
      "id": "1394746531849199618",
      "url": "https://twitter.com/BlueOc1981/1394746531849199618",
      "user": "BlueOc1981",
      "sentiment": -0.4574
    },
    {
      "id": "1394746892307816451",
      "url": "https://twitter.com/EvaNP23/1394746892307816451",
      "user": "EvaNP23",
      "sentiment": 0.6705
    },
    {
      "id": "1394746077887098880",
      "url": "https://twitter.com/OWLSI1/1394746077887098880",
      "user": "OWLSI1",
      "sentiment": 0.0
    },
    {
      "id": "1394743568753823746",
      "url": "https://twitter.com/BlueOc1981/1394743568753823746",
      "user": "BlueOc1981",
      "sentiment": 0.9022
    },
    {
      "id": "1394742420210806784",
      "url": "https://twitter.com/tidalraver/1394742420210806784",
      "user": "tidalraver",
      "sentiment": -0.2023
    },
    {
      "id": "1394742627245957127",
      "url": "https://twitter.com/KwikWarren/1394742627245957127",
      "user": "KwikWarren",
      "sentiment": 0.5473
    },
    {
      "id": "1394737204556046337",
      "url": "https://twitter.com/DoD_Analyst/1394737204556046337",
      "user": "DoD_Analyst",
      "sentiment": -0.1531
    },
    {
      "id": "1394729828893528065",
      "url": "https://twitter.com/meldogone/1394729828893528065",
      "user": "meldogone",
      "sentiment": 0.4404
    },
    {
      "id": "1394728501840916483",
      "url": "https://twitter.com/indivisible_usa/1394728501840916483",
      "user": "indivisible_usa",
      "sentiment": -0.6369
    },
    {
      "id": "1394728852279136266",
      "url": "https://twitter.com/screaminglibral/1394728852279136266",
      "user": "screaminglibral",
      "sentiment": 0.0
    },
    {
      "id": "1394670974545670146",
      "url": "https://twitter.com/screaminglibral/1394670974545670146",
      "user": "screaminglibral",
      "sentiment": -0.4753
    },
    {
      "id": "1394726271771365376",
      "url": "https://twitter.com/indivisible_usa/1394726271771365376",
      "user": "indivisible_usa",
      "sentiment": 0.5815
    },
    {
      "id": "1394725210134392838",
      "url": "https://twitter.com/LizWill99/1394725210134392838",
      "user": "LizWill99",
      "sentiment": -0.5994
    },
    {
      "id": "1394724949621985282",
      "url": "https://twitter.com/carlettej1/1394724949621985282",
      "user": "carlettej1",
      "sentiment": -0.4019
    },
    {
      "id": "1394722992890994694",
      "url": "https://twitter.com/sue_again/1394722992890994694",
      "user": "sue_again",
      "sentiment": -0.5789
    },
    {
      "id": "1394722078004289549",
      "url": "https://twitter.com/efero_patricia/1394722078004289549",
      "user": "efero_patricia",
      "sentiment": -0.2057
    },
    {
      "id": "1394719053982232581",
      "url": "https://twitter.com/JAstford/1394719053982232581",
      "user": "JAstford",
      "sentiment": 0.0
    },
    {
      "id": "1394717166704996354",
      "url": "https://twitter.com/NYDKFL/1394717166704996354",
      "user": "NYDKFL",
      "sentiment": -0.4767
    },
    {
      "id": "1394670108811751427",
      "url": "https://twitter.com/kingminotaurs/1394670108811751427",
      "user": "kingminotaurs",
      "sentiment": -0.9136
    },
    {
      "id": "1394712698911342593",
      "url": "https://twitter.com/TheButt94936728/1394712698911342593",
      "user": "TheButt94936728",
      "sentiment": -0.6369
    },
    {
      "id": "1394711148621074435",
      "url": "https://twitter.com/BenNiderberg/1394711148621074435",
      "user": "BenNiderberg",
      "sentiment": 0.0
    },
    {
      "id": "1394710557589217282",
      "url": "https://twitter.com/JLownLaw/1394710557589217282",
      "user": "JLownLaw",
      "sentiment": 0.1901
    },
    {
      "id": "1394707598251864067",
      "url": "https://twitter.com/thomasntexas/1394707598251864067",
      "user": "thomasntexas",
      "sentiment": -0.4023
    },
    {
      "id": "1394706933202968578",
      "url": "https://twitter.com/PieperLee/1394706933202968578",
      "user": "PieperLee",
      "sentiment": 0.0
    },
    {
      "id": "1394705953816121348",
      "url": "https://twitter.com/LMET1111/1394705953816121348",
      "user": "LMET1111",
      "sentiment": 0.7121
    },
    {
      "id": "1394671662713516033",
      "url": "https://twitter.com/KwikWarren/1394671662713516033",
      "user": "KwikWarren",
      "sentiment": 0.0
    },
    {
      "id": "1394704819353538560",
      "url": "https://twitter.com/4thViv/1394704819353538560",
      "user": "4thViv",
      "sentiment": 0.6852
    },
    {
      "id": "1394703793799921673",
      "url": "https://twitter.com/miakkamisfit57/1394703793799921673",
      "user": "miakkamisfit57",
      "sentiment": 0.4588
    },
    {
      "id": "1394674381092278274",
      "url": "https://twitter.com/JamesFLoveIV/1394674381092278274",
      "user": "JamesFLoveIV",
      "sentiment": -0.296
    },
    {
      "id": "1394703205150466051",
      "url": "https://twitter.com/4thViv/1394703205150466051",
      "user": "4thViv",
      "sentiment": 0.0
    },
    {
      "id": "1394664216452210692",
      "url": "https://twitter.com/AnydalyAmy/1394664216452210692",
      "user": "AnydalyAmy",
      "sentiment": 0.5095
    },
    {
      "id": "1394701561088016386",
      "url": "https://twitter.com/hjelle_brian/1394701561088016386",
      "user": "hjelle_brian",
      "sentiment": -0.7003
    },
    {
      "id": "1394698408049487874",
      "url": "https://twitter.com/jillyphil45/1394698408049487874",
      "user": "jillyphil45",
      "sentiment": 0.5423
    },
    {
      "id": "1394696032500346881",
      "url": "https://twitter.com/JelliDonut/1394696032500346881",
      "user": "JelliDonut",
      "sentiment": -0.6986
    },
    {
      "id": "1394695763205165061",
      "url": "https://twitter.com/memehoward/1394695763205165061",
      "user": "memehoward",
      "sentiment": 0.6369
    },
    {
      "id": "1394695662323871747",
      "url": "https://twitter.com/nealegroup/1394695662323871747",
      "user": "nealegroup",
      "sentiment": 0.8442
    },
    {
      "id": "1394686404572049412",
      "url": "https://twitter.com/TruBluMarin/1394686404572049412",
      "user": "TruBluMarin",
      "sentiment": 0.0
    },
    {
      "id": "1394693698626015232",
      "url": "https://twitter.com/alligatoreggs/1394693698626015232",
      "user": "alligatoreggs",
      "sentiment": 0.8779
    },
    {
      "id": "1394647326262808576",
      "url": "https://twitter.com/KwikWarren/1394647326262808576",
      "user": "KwikWarren",
      "sentiment": 0.0018
    },
    {
      "id": "1394691525951557650",
      "url": "https://twitter.com/Lindademocat/1394691525951557650",
      "user": "Lindademocat",
      "sentiment": 0.0
    },
    {
      "id": "1394669428588126210",
      "url": "https://twitter.com/KwikWarren/1394669428588126210",
      "user": "KwikWarren",
      "sentiment": -0.7906
    },
    {
      "id": "1394691228218834946",
      "url": "https://twitter.com/Lindademocat/1394691228218834946",
      "user": "Lindademocat",
      "sentiment": 0.0
    },
    {
      "id": "1394690918414966787",
      "url": "https://twitter.com/KardaszMichelle/1394690918414966787",
      "user": "KardaszMichelle",
      "sentiment": 0.3612
    },
    {
      "id": "1394689156564099082",
      "url": "https://twitter.com/ShanVWUUTK/1394689156564099082",
      "user": "ShanVWUUTK",
      "sentiment": 0.2732
    },
    {
      "id": "1394689119046049803",
      "url": "https://twitter.com/mamandebullies/1394689119046049803",
      "user": "mamandebullies",
      "sentiment": 0.128
    },
    {
      "id": "1394687800969154560",
      "url": "https://twitter.com/Logar539/1394687800969154560",
      "user": "Logar539",
      "sentiment": 0.5574
    },
    {
      "id": "1394687172247130113",
      "url": "https://twitter.com/KoaCalifornia/1394687172247130113",
      "user": "KoaCalifornia",
      "sentiment": 0.7717
    },
    {
      "id": "1394686487384502275",
      "url": "https://twitter.com/rchiovoloni/1394686487384502275",
      "user": "rchiovoloni",
      "sentiment": -0.6249
    },
    {
      "id": "1394683197540106242",
      "url": "https://twitter.com/EricNeudel/1394683197540106242",
      "user": "EricNeudel",
      "sentiment": -0.0772
    },
    {
      "id": "1394682983555035138",
      "url": "https://twitter.com/Pea_Pock/1394682983555035138",
      "user": "Pea_Pock",
      "sentiment": 0.743
    },
    {
      "id": "1394682371534901255",
      "url": "https://twitter.com/RevJudyBG/1394682371534901255",
      "user": "RevJudyBG",
      "sentiment": -0.5574
    },
    {
      "id": "1394682261577027589",
      "url": "https://twitter.com/KwikWarren/1394682261577027589",
      "user": "KwikWarren",
      "sentiment": 0.0
    },
    {
      "id": "1394682367323873283",
      "url": "https://twitter.com/nicolazzo_e/1394682367323873283",
      "user": "nicolazzo_e",
      "sentiment": 0.6486
    },
    {
      "id": "1394682161882669062",
      "url": "https://twitter.com/nicolazzo_e/1394682161882669062",
      "user": "nicolazzo_e",
      "sentiment": -0.6249
    },
    {
      "id": "1394681536964923397",
      "url": "https://twitter.com/skybluewoman2/1394681536964923397",
      "user": "skybluewoman2",
      "sentiment": 0.0
    },
    {
      "id": "1394678566055387136",
      "url": "https://twitter.com/lyndy1115/1394678566055387136",
      "user": "lyndy1115",
      "sentiment": 0.0
    },
    {
      "id": "1394678496853585932",
      "url": "https://twitter.com/TroutlineCreek/1394678496853585932",
      "user": "TroutlineCreek",
      "sentiment": 0.0772
    },
    {
      "id": "1394678002353508354",
      "url": "https://twitter.com/shellydogg/1394678002353508354",
      "user": "shellydogg",
      "sentiment": -0.466
    },
    {
      "id": "1394677199022837760",
      "url": "https://twitter.com/ACanadianinUSA/1394677199022837760",
      "user": "ACanadianinUSA",
      "sentiment": 0.9064
    },
    {
      "id": "1394672883918585857",
      "url": "https://twitter.com/bannedaid58/1394672883918585857",
      "user": "bannedaid58",
      "sentiment": -0.1263
    },
    {
      "id": "1394674919229775876",
      "url": "https://twitter.com/KatieRedvoteblu/1394674919229775876",
      "user": "KatieRedvoteblu",
      "sentiment": 0.0
    },
    {
      "id": "1394664507587313667",
      "url": "https://twitter.com/4thViv/1394664507587313667",
      "user": "4thViv",
      "sentiment": 0.3612
    },
    {
      "id": "1394674061934923776",
      "url": "https://twitter.com/52Katydid/1394674061934923776",
      "user": "52Katydid",
      "sentiment": -0.2382
    },
    {
      "id": "1394672536747663362",
      "url": "https://twitter.com/bannedaid58/1394672536747663362",
      "user": "bannedaid58",
      "sentiment": 0.3387
    },
    {
      "id": "1394673424115453958",
      "url": "https://twitter.com/52Katydid/1394673424115453958",
      "user": "52Katydid",
      "sentiment": 0.0
    },
    {
      "id": "1394673392415092743",
      "url": "https://twitter.com/Kayema42/1394673392415092743",
      "user": "Kayema42",
      "sentiment": 0.0
    },
    {
      "id": "1394673368733937666",
      "url": "https://twitter.com/jeepturners/1394673368733937666",
      "user": "jeepturners",
      "sentiment": -0.8057
    },
    {
      "id": "1394673299448377344",
      "url": "https://twitter.com/Wingsfan408/1394673299448377344",
      "user": "Wingsfan408",
      "sentiment": 0.6808
    },
    {
      "id": "1394673060754558976",
      "url": "https://twitter.com/emkatepsu/1394673060754558976",
      "user": "emkatepsu",
      "sentiment": 0.0644
    },
    {
      "id": "1394672835830849539",
      "url": "https://twitter.com/2Alarm/1394672835830849539",
      "user": "2Alarm",
      "sentiment": 0.0
    },
    {
      "id": "1394672782600978440",
      "url": "https://twitter.com/NHadgisava/1394672782600978440",
      "user": "NHadgisava",
      "sentiment": 0.0
    },
    {
      "id": "1394672327007379460",
      "url": "https://twitter.com/cakenewsnext/1394672327007379460",
      "user": "cakenewsnext",
      "sentiment": 0.8625
    },
    {
      "id": "1394672767388246017",
      "url": "https://twitter.com/KwikWarren/1394672767388246017",
      "user": "KwikWarren",
      "sentiment": 0.0
    },
    {
      "id": "1394642601685360646",
      "url": "https://twitter.com/KaronWilson4/1394642601685360646",
      "user": "KaronWilson4",
      "sentiment": -0.5859
    },
    {
      "id": "1394671983133003782",
      "url": "https://twitter.com/angelaadcock02/1394671983133003782",
      "user": "angelaadcock02",
      "sentiment": 0.2942
    },
    {
      "id": "1394671677674512391",
      "url": "https://twitter.com/Marianne61/1394671677674512391",
      "user": "Marianne61",
      "sentiment": 0.0088
    },
    {
      "id": "1394669933439733762",
      "url": "https://twitter.com/4thViv/1394669933439733762",
      "user": "4thViv",
      "sentiment": -0.0772
    },
    {
      "id": "1394670960419086337",
      "url": "https://twitter.com/AnydalyAmy/1394670960419086337",
      "user": "AnydalyAmy",
      "sentiment": 0.8591
    },
    {
      "id": "1394671211012136967",
      "url": "https://twitter.com/RayneMillaray/1394671211012136967",
      "user": "RayneMillaray",
      "sentiment": 0.6705
    },
    {
      "id": "1394648172559958025",
      "url": "https://twitter.com/RayneMillaray/1394648172559958025",
      "user": "RayneMillaray",
      "sentiment": 0.4785
    },
    {
      "id": "1394670791724306436",
      "url": "https://twitter.com/screaminglibral/1394670791724306436",
      "user": "screaminglibral",
      "sentiment": 0.2422
    },
    {
      "id": "1394670493454774285",
      "url": "https://twitter.com/ChuckMcCullagh/1394670493454774285",
      "user": "ChuckMcCullagh",
      "sentiment": 0.7003
    },
    {
      "id": "1394670149878308870",
      "url": "https://twitter.com/MadHabber/1394670149878308870",
      "user": "MadHabber",
      "sentiment": 0.0772
    },
    {
      "id": "1394668066483605511",
      "url": "https://twitter.com/NightclubGenius/1394668066483605511",
      "user": "NightclubGenius",
      "sentiment": -0.8381
    },
    {
      "id": "1394664906478309376",
      "url": "https://twitter.com/KwikWarren/1394664906478309376",
      "user": "KwikWarren",
      "sentiment": 0.2023
    },
    {
      "id": "1394668894154022918",
      "url": "https://twitter.com/p_hounds/1394668894154022918",
      "user": "p_hounds",
      "sentiment": 0.0
    },
    {
      "id": "1394669667361476610",
      "url": "https://twitter.com/KwikWarren/1394669667361476610",
      "user": "KwikWarren",
      "sentiment": 0.5473
    },
    {
      "id": "1394669642262585346",
      "url": "https://twitter.com/Solarman1955/1394669642262585346",
      "user": "Solarman1955",
      "sentiment": -0.0772
    },
    {
      "id": "1394669544027967496",
      "url": "https://twitter.com/Butler4Florida/1394669544027967496",
      "user": "Butler4Florida",
      "sentiment": 0.1877
    },
    {
      "id": "1394668917751123973",
      "url": "https://twitter.com/shawn_keren/1394668917751123973",
      "user": "shawn_keren",
      "sentiment": -0.4019
    },
    {
      "id": "1394668242686382085",
      "url": "https://twitter.com/cdeeter2/1394668242686382085",
      "user": "cdeeter2",
      "sentiment": 0.0
    },
    {
      "id": "1394668470743310343",
      "url": "https://twitter.com/KwikWarren/1394668470743310343",
      "user": "KwikWarren",
      "sentiment": -0.128
    },
    {
      "id": "1394667944882458625",
      "url": "https://twitter.com/PattiZander/1394667944882458625",
      "user": "PattiZander",
      "sentiment": 0.577
    },
    {
      "id": "1394646158157520896",
      "url": "https://twitter.com/janeworld1/1394646158157520896",
      "user": "janeworld1",
      "sentiment": -0.6133
    },
    {
      "id": "1394667818583400452",
      "url": "https://twitter.com/le_ladydi410/1394667818583400452",
      "user": "le_ladydi410",
      "sentiment": -0.7351
    },
    {
      "id": "1394666683974000640",
      "url": "https://twitter.com/Nasty_Mindy/1394666683974000640",
      "user": "Nasty_Mindy",
      "sentiment": -0.4168
    },
    {
      "id": "1394666681801314319",
      "url": "https://twitter.com/Kkroskow/1394666681801314319",
      "user": "Kkroskow",
      "sentiment": 0.0
    },
    {
      "id": "1394666507070631938",
      "url": "https://twitter.com/richlocus/1394666507070631938",
      "user": "richlocus",
      "sentiment": 0.0
    },
    {
      "id": "1394666433955704833",
      "url": "https://twitter.com/Lucear510_/1394666433955704833",
      "user": "Lucear510_",
      "sentiment": 0.3612
    },
    {
      "id": "1394627232627372033",
      "url": "https://twitter.com/Lindademocat/1394627232627372033",
      "user": "Lindademocat",
      "sentiment": -0.6597
    },
    {
      "id": "1394666410836692992",
      "url": "https://twitter.com/Lucear510_/1394666410836692992",
      "user": "Lucear510_",
      "sentiment": 0.3612
    },
    {
      "id": "1394665981985927174",
      "url": "https://twitter.com/katestringer10/1394665981985927174",
      "user": "katestringer10",
      "sentiment": -0.4364
    },
    {
      "id": "1394665980987682816",
      "url": "https://twitter.com/harleyb11/1394665980987682816",
      "user": "harleyb11",
      "sentiment": 0.0772
    },
    {
      "id": "1394665701739094022",
      "url": "https://twitter.com/dougiepen/1394665701739094022",
      "user": "dougiepen",
      "sentiment": -0.5423
    },
    {
      "id": "1394664229333086209",
      "url": "https://twitter.com/4thViv/1394664229333086209",
      "user": "4thViv",
      "sentiment": -0.6486
    },
    {
      "id": "1394625607011536902",
      "url": "https://twitter.com/JamesFLoveIV/1394625607011536902",
      "user": "JamesFLoveIV",
      "sentiment": 0.0
    },
    {
      "id": "1394639935609606157",
      "url": "https://twitter.com/hjelle_brian/1394639935609606157",
      "user": "hjelle_brian",
      "sentiment": 0.4767
    },
    {
      "id": "1394636804394037248",
      "url": "https://twitter.com/BooksRule54/1394636804394037248",
      "user": "BooksRule54",
      "sentiment": 0.0
    },
    {
      "id": "1394663068546715649",
      "url": "https://twitter.com/EarlHal55711627/1394663068546715649",
      "user": "EarlHal55711627",
      "sentiment": 0.7096
    },
    {
      "id": "1394647896436482048",
      "url": "https://twitter.com/KwikWarren/1394647896436482048",
      "user": "KwikWarren",
      "sentiment": -0.1901
    },
    {
      "id": "1394663058505715717",
      "url": "https://twitter.com/4thViv/1394663058505715717",
      "user": "4thViv",
      "sentiment": 0.5859
    },
    {
      "id": "1394661594102128645",
      "url": "https://twitter.com/KwikWarren/1394661594102128645",
      "user": "KwikWarren",
      "sentiment": 0.0
    },
    {
      "id": "1394661536665321472",
      "url": "https://twitter.com/PartyPolitical7/1394661536665321472",
      "user": "PartyPolitical7",
      "sentiment": -0.7717
    },
    {
      "id": "1394661129918586886",
      "url": "https://twitter.com/GenJackTRipper/1394661129918586886",
      "user": "GenJackTRipper",
      "sentiment": 0.0
    },
    {
      "id": "1394661097601372160",
      "url": "https://twitter.com/GenJackTRipper/1394661097601372160",
      "user": "GenJackTRipper",
      "sentiment": 0.0
    },
    {
      "id": "1394658757779632135",
      "url": "https://twitter.com/davidnist/1394658757779632135",
      "user": "davidnist",
      "sentiment": 0.6479
    },
    {
      "id": "1394660515918585856",
      "url": "https://twitter.com/MultChoiceMedia/1394660515918585856",
      "user": "MultChoiceMedia",
      "sentiment": 0.3818
    },
    {
      "id": "1394660397874130944",
      "url": "https://twitter.com/CharlieD1951/1394660397874130944",
      "user": "CharlieD1951",
      "sentiment": 0.296
    },
    {
      "id": "1394659409335181317",
      "url": "https://twitter.com/ajpbo/1394659409335181317",
      "user": "ajpbo",
      "sentiment": 0.0
    },
    {
      "id": "1394659645789294595",
      "url": "https://twitter.com/KwikWarren/1394659645789294595",
      "user": "KwikWarren",
      "sentiment": 0.0
    },
    {
      "id": "1394655727285903367",
      "url": "https://twitter.com/FutrellDenice/1394655727285903367",
      "user": "FutrellDenice",
      "sentiment": 0.629
    },
    {
      "id": "1394659539325173760",
      "url": "https://twitter.com/KwikWarren/1394659539325173760",
      "user": "KwikWarren",
      "sentiment": 0.4939
    },
    {
      "id": "1394656198197235721",
      "url": "https://twitter.com/shadetr40794574/1394656198197235721",
      "user": "shadetr40794574",
      "sentiment": 0.933
    },
    {
      "id": "1394659364003368963",
      "url": "https://twitter.com/KwikWarren/1394659364003368963",
      "user": "KwikWarren",
      "sentiment": 0.0
    },
    {
      "id": "1394659194108878854",
      "url": "https://twitter.com/susannaspeaks5/1394659194108878854",
      "user": "susannaspeaks5",
      "sentiment": 0.0
    },
    {
      "id": "1394659136051220482",
      "url": "https://twitter.com/PeterWe22707141/1394659136051220482",
      "user": "PeterWe22707141",
      "sentiment": -0.8519
    },
    {
      "id": "1394657185796263939",
      "url": "https://twitter.com/BailieCandace/1394657185796263939",
      "user": "BailieCandace",
      "sentiment": -0.705
    },
    {
      "id": "1394659110071771138",
      "url": "https://twitter.com/KwikWarren/1394659110071771138",
      "user": "KwikWarren",
      "sentiment": 0.2732
    },
    {
      "id": "1394658798166548492",
      "url": "https://twitter.com/NJdoc/1394658798166548492",
      "user": "NJdoc",
      "sentiment": 0.0
    },
    {
      "id": "1394654232083681282",
      "url": "https://twitter.com/MultChoiceMedia/1394654232083681282",
      "user": "MultChoiceMedia",
      "sentiment": -0.891
    },
    {
      "id": "1394658660693934086",
      "url": "https://twitter.com/SilverB38639385/1394658660693934086",
      "user": "SilverB38639385",
      "sentiment": -0.8477
    },
    {
      "id": "1394658605735964672",
      "url": "https://twitter.com/Duncanivez/1394658605735964672",
      "user": "Duncanivez",
      "sentiment": 0.2263
    },
    {
      "id": "1394657591658156033",
      "url": "https://twitter.com/KwikWarren/1394657591658156033",
      "user": "KwikWarren",
      "sentiment": -0.9079
    },
    {
      "id": "1394658137039200259",
      "url": "https://twitter.com/cherievann/1394658137039200259",
      "user": "cherievann",
      "sentiment": -0.4215
    },
    {
      "id": "1394657777566601219",
      "url": "https://twitter.com/eleanor2600/1394657777566601219",
      "user": "eleanor2600",
      "sentiment": 0.0
    },
    {
      "id": "1394657596221571080",
      "url": "https://twitter.com/hardyt69/1394657596221571080",
      "user": "hardyt69",
      "sentiment": 0.0
    },
    {
      "id": "1394653860250091523",
      "url": "https://twitter.com/cherievann/1394653860250091523",
      "user": "cherievann",
      "sentiment": 0.7339
    },
    {
      "id": "1394656683801006086",
      "url": "https://twitter.com/SilverB38639385/1394656683801006086",
      "user": "SilverB38639385",
      "sentiment": 0.567
    },
    {
      "id": "1394656586023542788",
      "url": "https://twitter.com/poshgurl/1394656586023542788",
      "user": "poshgurl",
      "sentiment": 0.8217
    },
    {
      "id": "1394655386133745668",
      "url": "https://twitter.com/charrispwd/1394655386133745668",
      "user": "charrispwd",
      "sentiment": -0.6124
    },
    {
      "id": "1394654736431808514",
      "url": "https://twitter.com/nfaac4/1394654736431808514",
      "user": "nfaac4",
      "sentiment": 0.6369
    },
    {
      "id": "1394654011823849473",
      "url": "https://twitter.com/GeniusLR/1394654011823849473",
      "user": "GeniusLR",
      "sentiment": 0.0
    },
    {
      "id": "1394653841736536064",
      "url": "https://twitter.com/PetrijennN/1394653841736536064",
      "user": "PetrijennN",
      "sentiment": 0.4574
    },
    {
      "id": "1394653531731374093",
      "url": "https://twitter.com/eswashburn64/1394653531731374093",
      "user": "eswashburn64",
      "sentiment": -0.162
    },
    {
      "id": "1394653384217595909",
      "url": "https://twitter.com/t_humper90/1394653384217595909",
      "user": "t_humper90",
      "sentiment": -0.4019
    },
    {
      "id": "1394638796646273025",
      "url": "https://twitter.com/SarcasticHoney/1394638796646273025",
      "user": "SarcasticHoney",
      "sentiment": 0.1901
    },
    {
      "id": "1394653373194903552",
      "url": "https://twitter.com/CrazyOldLady10/1394653373194903552",
      "user": "CrazyOldLady10",
      "sentiment": 0.1531
    },
    {
      "id": "1394653213052358660",
      "url": "https://twitter.com/MGScott9/1394653213052358660",
      "user": "MGScott9",
      "sentiment": -0.1363
    },
    {
      "id": "1394652622624284673",
      "url": "https://twitter.com/elevatorpiitch/1394652622624284673",
      "user": "elevatorpiitch",
      "sentiment": 0.1779
    },
    {
      "id": "1394652832381513731",
      "url": "https://twitter.com/KwikWarren/1394652832381513731",
      "user": "KwikWarren",
      "sentiment": -0.5095
    },
    {
      "id": "1394652447847731201",
      "url": "https://twitter.com/BabsonJeremy/1394652447847731201",
      "user": "BabsonJeremy",
      "sentiment": -0.9231
    },
    {
      "id": "1394652268205690885",
      "url": "https://twitter.com/hi_pah/1394652268205690885",
      "user": "hi_pah",
      "sentiment": -0.9108
    },
    {
      "id": "1394651061030461450",
      "url": "https://twitter.com/paulabagwell3/1394651061030461450",
      "user": "paulabagwell3",
      "sentiment": 0.0
    },
    {
      "id": "1394651451797000193",
      "url": "https://twitter.com/KwikWarren/1394651451797000193",
      "user": "KwikWarren",
      "sentiment": 0.296
    },
    {
      "id": "1394650270236299271",
      "url": "https://twitter.com/KwikWarren/1394650270236299271",
      "user": "KwikWarren",
      "sentiment": 0.7096
    },
    {
      "id": "1394651388609802241",
      "url": "https://twitter.com/RayneMillaray/1394651388609802241",
      "user": "RayneMillaray",
      "sentiment": 0.7096
    },
    {
      "id": "1394634672408236034",
      "url": "https://twitter.com/annette0626/1394634672408236034",
      "user": "annette0626",
      "sentiment": -0.6135
    },
    {
      "id": "1394651035441016834",
      "url": "https://twitter.com/rossaarose/1394651035441016834",
      "user": "rossaarose",
      "sentiment": -0.6588
    },
    {
      "id": "1394650960136339457",
      "url": "https://twitter.com/se_kirks/1394650960136339457",
      "user": "se_kirks",
      "sentiment": 0.0
    },
    {
      "id": "1394631938498048003",
      "url": "https://twitter.com/chicago21222/1394631938498048003",
      "user": "chicago21222",
      "sentiment": -0.8898
    },
    {
      "id": "1394650544841674752",
      "url": "https://twitter.com/KwikWarren/1394650544841674752",
      "user": "KwikWarren",
      "sentiment": 0.0
    },
    {
      "id": "1394648319700262914",
      "url": "https://twitter.com/BombayLace/1394648319700262914",
      "user": "BombayLace",
      "sentiment": 0.5106
    },
    {
      "id": "1394650028967403523",
      "url": "https://twitter.com/KwikWarren/1394650028967403523",
      "user": "KwikWarren",
      "sentiment": 0.5473
    },
    {
      "id": "1394650012513099788",
      "url": "https://twitter.com/lakeeriejake/1394650012513099788",
      "user": "lakeeriejake",
      "sentiment": 0.5994
    },
    {
      "id": "1394649921609994245",
      "url": "https://twitter.com/CefTweets/1394649921609994245",
      "user": "CefTweets",
      "sentiment": 0.2083
    },
    {
      "id": "1394648922732199944",
      "url": "https://twitter.com/TheWriteJennyG/1394648922732199944",
      "user": "TheWriteJennyG",
      "sentiment": -0.0772
    },
    {
      "id": "1394649918241972225",
      "url": "https://twitter.com/KwikWarren/1394649918241972225",
      "user": "KwikWarren",
      "sentiment": -0.5719
    },
    {
      "id": "1394649670337634311",
      "url": "https://twitter.com/Book_Lady_127/1394649670337634311",
      "user": "Book_Lady_127",
      "sentiment": 0.1901
    },
    {
      "id": "1394648115173634050",
      "url": "https://twitter.com/AndreaTurkalo/1394648115173634050",
      "user": "AndreaTurkalo",
      "sentiment": -0.128
    },
    {
      "id": "1394648932710502400",
      "url": "https://twitter.com/BooksRule54/1394648932710502400",
      "user": "BooksRule54",
      "sentiment": 0.0
    },
    {
      "id": "1394648741513109511",
      "url": "https://twitter.com/HollieJoyJoy/1394648741513109511",
      "user": "HollieJoyJoy",
      "sentiment": 0.0
    },
    {
      "id": "1394634406812344322",
      "url": "https://twitter.com/BooksRule54/1394634406812344322",
      "user": "BooksRule54",
      "sentiment": 0.2732
    },
    {
      "id": "1394648051591966720",
      "url": "https://twitter.com/TheWriteJennyG/1394648051591966720",
      "user": "TheWriteJennyG",
      "sentiment": 0.4404
    },
    {
      "id": "1394648049809559553",
      "url": "https://twitter.com/onebluesky4/1394648049809559553",
      "user": "onebluesky4",
      "sentiment": -0.1144
    },
    {
      "id": "1394647338669510663",
      "url": "https://twitter.com/JoyceMJeffries1/1394647338669510663",
      "user": "JoyceMJeffries1",
      "sentiment": -0.7351
    },
    {
      "id": "1394647415513403395",
      "url": "https://twitter.com/KwikWarren/1394647415513403395",
      "user": "KwikWarren",
      "sentiment": 0.0
    },
    {
      "id": "1394646364651331590",
      "url": "https://twitter.com/randyfraz/1394646364651331590",
      "user": "randyfraz",
      "sentiment": 0.5106
    },
    {
      "id": "1394646359563722754",
      "url": "https://twitter.com/karenkmason1/1394646359563722754",
      "user": "karenkmason1",
      "sentiment": 0.0
    },
    {
      "id": "1394626331644661763",
      "url": "https://twitter.com/KwikWarren/1394626331644661763",
      "user": "KwikWarren",
      "sentiment": 0.0
    },
    {
      "id": "1394645789146697728",
      "url": "https://twitter.com/cherievann/1394645789146697728",
      "user": "cherievann",
      "sentiment": 0.0
    },
    {
      "id": "1394643320798949383",
      "url": "https://twitter.com/LitterBoxBlues/1394643320798949383",
      "user": "LitterBoxBlues",
      "sentiment": 0.3802
    },
    {
      "id": "1394642960109772801",
      "url": "https://twitter.com/wedietz/1394642960109772801",
      "user": "wedietz",
      "sentiment": -0.854
    },
    {
      "id": "1394642331551375361",
      "url": "https://twitter.com/Siadasha/1394642331551375361",
      "user": "Siadasha",
      "sentiment": -0.128
    },
    {
      "id": "1394642252396388359",
      "url": "https://twitter.com/CookKCEgyptian/1394642252396388359",
      "user": "CookKCEgyptian",
      "sentiment": 0.4738
    },
    {
      "id": "1394641188909719555",
      "url": "https://twitter.com/layr951/1394641188909719555",
      "user": "layr951",
      "sentiment": 0.5423
    },
    {
      "id": "1394640061077942279",
      "url": "https://twitter.com/mouthy_the/1394640061077942279",
      "user": "mouthy_the",
      "sentiment": 0.0
    },
    {
      "id": "1394640020405952516",
      "url": "https://twitter.com/damkina/1394640020405952516",
      "user": "damkina",
      "sentiment": 0.0
    },
    {
      "id": "1394639839463714819",
      "url": "https://twitter.com/cathy_greenman/1394639839463714819",
      "user": "cathy_greenman",
      "sentiment": 0.6239
    },
    {
      "id": "1394639819045838851",
      "url": "https://twitter.com/DESciulli/1394639819045838851",
      "user": "DESciulli",
      "sentiment": -0.3182
    },
    {
      "id": "1394639805330247685",
      "url": "https://twitter.com/garrisonfarm1/1394639805330247685",
      "user": "garrisonfarm1",
      "sentiment": 0.0
    },
    {
      "id": "1394634868890345476",
      "url": "https://twitter.com/CrazyOldLady10/1394634868890345476",
      "user": "CrazyOldLady10",
      "sentiment": 0.9604
    },
    {
      "id": "1394638169619017729",
      "url": "https://twitter.com/SPesteritis/1394638169619017729",
      "user": "SPesteritis",
      "sentiment": -0.4003
    },
    {
      "id": "1394638100714999816",
      "url": "https://twitter.com/bridgetsimonds0/1394638100714999816",
      "user": "bridgetsimonds0",
      "sentiment": 0.6369
    },
    {
      "id": "1394637957462642690",
      "url": "https://twitter.com/DianeToucan/1394637957462642690",
      "user": "DianeToucan",
      "sentiment": -0.1027
    },
    {
      "id": "1394637477663547393",
      "url": "https://twitter.com/SarcasticHoney/1394637477663547393",
      "user": "SarcasticHoney",
      "sentiment": 0.8591
    },
    {
      "id": "1394634536055619588",
      "url": "https://twitter.com/KwikWarren/1394634536055619588",
      "user": "KwikWarren",
      "sentiment": -0.5423
    },
    {
      "id": "1394637466930487298",
      "url": "https://twitter.com/BooksRule54/1394637466930487298",
      "user": "BooksRule54",
      "sentiment": -0.128
    },
    {
      "id": "1394637079456460805",
      "url": "https://twitter.com/MaureenManos/1394637079456460805",
      "user": "MaureenManos",
      "sentiment": -0.0772
    },
    {
      "id": "1394621545629327367",
      "url": "https://twitter.com/luvdafood/1394621545629327367",
      "user": "luvdafood",
      "sentiment": 0.0
    },
    {
      "id": "1394637042257117191",
      "url": "https://twitter.com/BooksRule54/1394637042257117191",
      "user": "BooksRule54",
      "sentiment": -0.3612
    },
    {
      "id": "1394635517166297088",
      "url": "https://twitter.com/pricklyeater/1394635517166297088",
      "user": "pricklyeater",
      "sentiment": -0.8812
    },
    {
      "id": "1394636730209226752",
      "url": "https://twitter.com/fransaundersays/1394636730209226752",
      "user": "fransaundersays",
      "sentiment": -0.8034
    },
    {
      "id": "1394636467792658432",
      "url": "https://twitter.com/smtf257/1394636467792658432",
      "user": "smtf257",
      "sentiment": -0.5423
    },
    {
      "id": "1394636456119967744",
      "url": "https://twitter.com/simbolism1/1394636456119967744",
      "user": "simbolism1",
      "sentiment": 0.0
    },
    {
      "id": "1394636175995019264",
      "url": "https://twitter.com/BooksRule54/1394636175995019264",
      "user": "BooksRule54",
      "sentiment": 0.2023
    },
    {
      "id": "1394636128158896131",
      "url": "https://twitter.com/andSandSandrags/1394636128158896131",
      "user": "andSandSandrags",
      "sentiment": 0.0
    },
    {
      "id": "1394635871501144064",
      "url": "https://twitter.com/RevJudyBG/1394635871501144064",
      "user": "RevJudyBG",
      "sentiment": -0.5346
    },
    {
      "id": "1394627212217888771",
      "url": "https://twitter.com/JamesFLoveIV/1394627212217888771",
      "user": "JamesFLoveIV",
      "sentiment": -0.5802
    },
    {
      "id": "1394635018971066371",
      "url": "https://twitter.com/BooksRule54/1394635018971066371",
      "user": "BooksRule54",
      "sentiment": -0.7003
    },
    {
      "id": "1394634704469516288",
      "url": "https://twitter.com/RustyBJohnson1/1394634704469516288",
      "user": "RustyBJohnson1",
      "sentiment": 0.0
    },
    {
      "id": "1394634089395855360",
      "url": "https://twitter.com/LynEpar/1394634089395855360",
      "user": "LynEpar",
      "sentiment": 0.0377
    },
    {
      "id": "1394633658246574080",
      "url": "https://twitter.com/Monique_Resists/1394633658246574080",
      "user": "Monique_Resists",
      "sentiment": -0.3071
    },
    {
      "id": "1394633263872978945",
      "url": "https://twitter.com/MJdowntheshore/1394633263872978945",
      "user": "MJdowntheshore",
      "sentiment": -0.2023
    },
    {
      "id": "1394633077020762115",
      "url": "https://twitter.com/mgtex/1394633077020762115",
      "user": "mgtex",
      "sentiment": 0.128
    },
    {
      "id": "1394632001718833156",
      "url": "https://twitter.com/VelvetDunn4/1394632001718833156",
      "user": "VelvetDunn4",
      "sentiment": -0.0772
    },
    {
      "id": "1394632705841811459",
      "url": "https://twitter.com/KwikWarren/1394632705841811459",
      "user": "KwikWarren",
      "sentiment": 0.0
    },
    {
      "id": "1394632615815172096",
      "url": "https://twitter.com/Giordan67551736/1394632615815172096",
      "user": "Giordan67551736",
      "sentiment": -0.6369
    },
    {
      "id": "1394632500278964224",
      "url": "https://twitter.com/ateacher97/1394632500278964224",
      "user": "ateacher97",
      "sentiment": 0.0281
    },
    {
      "id": "1394632419064549380",
      "url": "https://twitter.com/stewardlinda10/1394632419064549380",
      "user": "stewardlinda10",
      "sentiment": 0.0
    },
    {
      "id": "1394632242245292032",
      "url": "https://twitter.com/pbean25/1394632242245292032",
      "user": "pbean25",
      "sentiment": -0.128
    },
    {
      "id": "1394628221153464320",
      "url": "https://twitter.com/bannedaid58/1394628221153464320",
      "user": "bannedaid58",
      "sentiment": 0.6744
    },
    {
      "id": "1394632001886564354",
      "url": "https://twitter.com/gsagag/1394632001886564354",
      "user": "gsagag",
      "sentiment": 0.8402
    },
    {
      "id": "1394631109028335621",
      "url": "https://twitter.com/ctgibson/1394631109028335621",
      "user": "ctgibson",
      "sentiment": 0.7783
    },
    {
      "id": "1394630903222132742",
      "url": "https://twitter.com/SpencerMagne/1394630903222132742",
      "user": "SpencerMagne",
      "sentiment": 0.4199
    },
    {
      "id": "1394629716762456065",
      "url": "https://twitter.com/Stephan56189908/1394629716762456065",
      "user": "Stephan56189908",
      "sentiment": -0.4588
    },
    {
      "id": "1394630723504640000",
      "url": "https://twitter.com/JamesFLoveIV/1394630723504640000",
      "user": "JamesFLoveIV",
      "sentiment": -0.7096
    },
    {
      "id": "1394630590914256896",
      "url": "https://twitter.com/lula_reh/1394630590914256896",
      "user": "lula_reh",
      "sentiment": -0.4854
    },
    {
      "id": "1394630554117722115",
      "url": "https://twitter.com/Artie502/1394630554117722115",
      "user": "Artie502",
      "sentiment": -0.3818
    },
    {
      "id": "1394629829862043648",
      "url": "https://twitter.com/DeliaSheridan3/1394629829862043648",
      "user": "DeliaSheridan3",
      "sentiment": -0.0516
    },
    {
      "id": "1394629824593809415",
      "url": "https://twitter.com/nightcareoption/1394629824593809415",
      "user": "nightcareoption",
      "sentiment": -0.1573
    },
    {
      "id": "1394629499711594501",
      "url": "https://twitter.com/JB51304/1394629499711594501",
      "user": "JB51304",
      "sentiment": -0.024
    },
    {
      "id": "1394629405159432192",
      "url": "https://twitter.com/Prizzy6458/1394629405159432192",
      "user": "Prizzy6458",
      "sentiment": -0.0772
    },
    {
      "id": "1394627494066720770",
      "url": "https://twitter.com/Amatodeb/1394627494066720770",
      "user": "Amatodeb",
      "sentiment": 0.0
    },
    {
      "id": "1394627423736680448",
      "url": "https://twitter.com/redhed67/1394627423736680448",
      "user": "redhed67",
      "sentiment": 0.128
    },
    {
      "id": "1394627382255001602",
      "url": "https://twitter.com/suzybwell/1394627382255001602",
      "user": "suzybwell",
      "sentiment": 0.0258
    },
    {
      "id": "1394626434501578755",
      "url": "https://twitter.com/KwikWarren/1394626434501578755",
      "user": "KwikWarren",
      "sentiment": 0.0
    },
    {
      "id": "1394627374659084291",
      "url": "https://twitter.com/CarolynGarman5/1394627374659084291",
      "user": "CarolynGarman5",
      "sentiment": -0.816
    },
    {
      "id": "1394625897148338183",
      "url": "https://twitter.com/KwikWarren/1394625897148338183",
      "user": "KwikWarren",
      "sentiment": 0.2732
    },
    {
      "id": "1394626624432263172",
      "url": "https://twitter.com/deebelleisle/1394626624432263172",
      "user": "deebelleisle",
      "sentiment": -0.2411
    },
    {
      "id": "1394625754567225344",
      "url": "https://twitter.com/CarolynGarman5/1394625754567225344",
      "user": "CarolynGarman5",
      "sentiment": -0.743
    },
    {
      "id": "1394626425748086784",
      "url": "https://twitter.com/DonWickenhagen/1394626425748086784",
      "user": "DonWickenhagen",
      "sentiment": 0.3859
    },
    {
      "id": "1394625756475629574",
      "url": "https://twitter.com/GunnyJ/1394625756475629574",
      "user": "GunnyJ",
      "sentiment": 0.9423
    },
    {
      "id": "1394625667384422405",
      "url": "https://twitter.com/paulndor/1394625667384422405",
      "user": "paulndor",
      "sentiment": 0.0
    },
    {
      "id": "1394625359996391426",
      "url": "https://twitter.com/OldElnora/1394625359996391426",
      "user": "OldElnora",
      "sentiment": 0.2924
    },
    {
      "id": "1394625080039194626",
      "url": "https://twitter.com/dennisvalerino/1394625080039194626",
      "user": "dennisvalerino",
      "sentiment": -0.6249
    },
    {
      "id": "1394624891211681797",
      "url": "https://twitter.com/amandasmama/1394624891211681797",
      "user": "amandasmama",
      "sentiment": -0.796
    },
    {
      "id": "1394624743073013763",
      "url": "https://twitter.com/Msmoon54/1394624743073013763",
      "user": "Msmoon54",
      "sentiment": -0.3164
    },
    {
      "id": "1394620965900926977",
      "url": "https://twitter.com/flints1963/1394620965900926977",
      "user": "flints1963",
      "sentiment": -0.802
    },
    {
      "id": "1394624452617510917",
      "url": "https://twitter.com/KwikWarren/1394624452617510917",
      "user": "KwikWarren",
      "sentiment": 0.0
    },
    {
      "id": "1394624255019601921",
      "url": "https://twitter.com/Nanette_Marie1/1394624255019601921",
      "user": "Nanette_Marie1",
      "sentiment": -0.296
    },
    {
      "id": "1394624200657326083",
      "url": "https://twitter.com/KwikWarren/1394624200657326083",
      "user": "KwikWarren",
      "sentiment": 0.2732
    },
    {
      "id": "1394624068998021121",
      "url": "https://twitter.com/dingmanschoice/1394624068998021121",
      "user": "dingmanschoice",
      "sentiment": -0.5994
    },
    {
      "id": "1394624025247326215",
      "url": "https://twitter.com/BravardDr/1394624025247326215",
      "user": "BravardDr",
      "sentiment": -0.3016
    },
    {
      "id": "1394623978975735810",
      "url": "https://twitter.com/WhitehurstJr/1394623978975735810",
      "user": "WhitehurstJr",
      "sentiment": 0.0
    },
    {
      "id": "1394623957735776264",
      "url": "https://twitter.com/lmac522/1394623957735776264",
      "user": "lmac522",
      "sentiment": 0.5267
    },
    {
      "id": "1394623891679629315",
      "url": "https://twitter.com/hipsterbeeyotch/1394623891679629315",
      "user": "hipsterbeeyotch",
      "sentiment": 0.4574
    },
    {
      "id": "1394623545976754176",
      "url": "https://twitter.com/Richard_KT99/1394623545976754176",
      "user": "Richard_KT99",
      "sentiment": -0.3182
    },
    {
      "id": "1394623502699753475",
      "url": "https://twitter.com/beckstrom68/1394623502699753475",
      "user": "beckstrom68",
      "sentiment": 0.5423
    },
    {
      "id": "1394623150067945485",
      "url": "https://twitter.com/_businesscity/1394623150067945485",
      "user": "_businesscity",
      "sentiment": 0.3205
    },
    {
      "id": "1394623489211080706",
      "url": "https://twitter.com/KwikWarren/1394623489211080706",
      "user": "KwikWarren",
      "sentiment": 0.0
    },
    {
      "id": "1394622641970061319",
      "url": "https://twitter.com/ringwac/1394622641970061319",
      "user": "ringwac",
      "sentiment": 0.0
    },
    {
      "id": "1394622549066194952",
      "url": "https://twitter.com/StumpDrew/1394622549066194952",
      "user": "StumpDrew",
      "sentiment": 0.6476
    },
    {
      "id": "1394622474814377986",
      "url": "https://twitter.com/withanie1/1394622474814377986",
      "user": "withanie1",
      "sentiment": 0.1027
    },
    {
      "id": "1394622205485633536",
      "url": "https://twitter.com/d_veebee/1394622205485633536",
      "user": "d_veebee",
      "sentiment": -0.5859
    },
    {
      "id": "1394621809430089729",
      "url": "https://twitter.com/ViolinsOnTV88/1394621809430089729",
      "user": "ViolinsOnTV88",
      "sentiment": 0.5478
    },
    {
      "id": "1394621003662249987",
      "url": "https://twitter.com/GerualA/1394621003662249987",
      "user": "GerualA",
      "sentiment": 0.0
    }
  ],
  "edges": [
    [
      "1395518032785526787",
      "1395392514794872836"
    ],
    [
      "1395519706912657408",
      "1395518032785526787"
    ],
    [
      "1395392514794872836",
      "1395391370274037769"
    ],
    [
      "1395391370274037769",
      "1394620329662746627"
    ],
    [
      "1395320788501233671",
      "1394645905706467334"
    ],
    [
      "1395379083983265810",
      "1395320788501233671"
    ],
    [
      "1395317929319694340",
      "1394620329662746627"
    ],
    [
      "1395340270321950722",
      "1395317929319694340"
    ],
    [
      "1395318649737539590",
      "1394653253061816322"
    ],
    [
      "1395340130077052928",
      "1395318649737539590"
    ],
    [
      "1395340026754609152",
      "1395320788501233671"
    ],
    [
      "1394645905706467334",
      "1394645598322659331"
    ],
    [
      "1394645598322659331",
      "1394620329662746627"
    ],
    [
      "1395319131084189696",
      "1394645598322659331"
    ],
    [
      "1394653253061816322",
      "1394652776584654851"
    ],
    [
      "1395017988345110528",
      "1394762565318758408"
    ],
    [
      "1394976748891250689",
      "1394814086681088001"
    ],
    [
      "1394978243078393857",
      "1394976748891250689"
    ],
    [
      "1394814086681088001",
      "1394769708008751104"
    ],
    [
      "1394970668651921410",
      "1394620329662746627"
    ],
    [
      "1394971183423053826",
      "1394970668651921410"
    ],
    [
      "1394969686123630595",
      "1394620329662746627"
    ],
    [
      "1394666356482600963",
      "1394620329662746627"
    ],
    [
      "1394946481635971074",
      "1394666356482600963"
    ],
    [
      "1394946252958281731",
      "1394620329662746627"
    ],
    [
      "1394937075754049537",
      "1394814086681088001"
    ],
    [
      "1394879730940358659",
      "1394620329662746627"
    ],
    [
      "1394846439075942401",
      "1394620329662746627"
    ],
    [
      "1394832399486398465",
      "1394652776584654851"
    ],
    [
      "1394837186143473674",
      "1394832399486398465"
    ],
    [
      "1394832600473165825",
      "1394660122740150274"
    ],
    [
      "1394833740065542150",
      "1394832600473165825"
    ],
    [
      "1394624048496271366",
      "1394620329662746627"
    ],
    [
      "1394833494132596741",
      "1394624048496271366"
    ],
    [
      "1394660122740150274",
      "1394620329662746627"
    ],
    [
      "1394652776584654851",
      "1394620329662746627"
    ],
    [
      "1394821115403333633",
      "1394620329662746627"
    ],
    [
      "1394819494896312320",
      "1394620329662746627"
    ],
    [
      "1394820381979123716",
      "1394819494896312320"
    ],
    [
      "1394819948141158403",
      "1394819494896312320"
    ],
    [
      "1394620663739133956",
      "1394620329662746627"
    ],
    [
      "1394815299212484609",
      "1394620663739133956"
    ],
    [
      "1394769708008751104",
      "1394624048496271366"
    ],
    [
      "1394810567974662145",
      "1394620329662746627"
    ],
    [
      "1394809747270897669",
      "1394620329662746627"
    ],
    [
      "1394804878661193732",
      "1394620329662746627"
    ],
    [
      "1394802895799865348",
      "1394620329662746627"
    ],
    [
      "1394798888851316742",
      "1394620329662746627"
    ],
    [
      "1394794882137567234",
      "1394620329662746627"
    ],
    [
      "1394795086974787587",
      "1394794882137567234"
    ],
    [
      "1394784394150285315",
      "1394620329662746627"
    ],
    [
      "1394794736297336838",
      "1394784394150285315"
    ],
    [
      "1394793456397127681",
      "1394620329662746627"
    ],
    [
      "1394792948722765827",
      "1394620329662746627"
    ],
    [
      "1394789176730525697",
      "1394620329662746627"
    ],
    [
      "1394789031385436165",
      "1394620329662746627"
    ],
    [
      "1394663559318081538",
      "1394636804394037248"
    ],
    [
      "1394788444220665867",
      "1394663559318081538"
    ],
    [
      "1394769126141403146",
      "1394620329662746627"
    ],
    [
      "1394761900504666113",
      "1394620329662746627"
    ],
    [
      "1394756995589283845",
      "1394620329662746627"
    ],
    [
      "1394756925909176321",
      "1394620329662746627"
    ],
    [
      "1394750725364740097",
      "1394620329662746627"
    ],
    [
      "1394755979594633219",
      "1394750725364740097"
    ],
    [
      "1394755487921590274",
      "1394620329662746627"
    ],
    [
      "1394747900358389766",
      "1394747032070344705"
    ],
    [
      "1394751743058079747",
      "1394747900358389766"
    ],
    [
      "1394750666380390403",
      "1394620329662746627"
    ],
    [
      "1394749932100259844",
      "1394620329662746627"
    ],
    [
      "1394749436882915328",
      "1394620329662746627"
    ],
    [
      "1394749239201312777",
      "1394748802100236295"
    ],
    [
      "1394749369832902668",
      "1394749239201312777"
    ],
    [
      "1394749328804175877",
      "1394620329662746627"
    ],
    [
      "1394748802100236295",
      "1394620329662746627"
    ],
    [
      "1394748081174990854",
      "1394620329662746627"
    ],
    [
      "1394747032070344705",
      "1394746531849199618"
    ],
    [
      "1394746531849199618",
      "1394746077887098880"
    ],
    [
      "1394746892307816451",
      "1394652776584654851"
    ],
    [
      "1394746077887098880",
      "1394743568753823746"
    ],
    [
      "1394743568753823746",
      "1394620329662746627"
    ],
    [
      "1394742420210806784",
      "1394620329662746627"
    ],
    [
      "1394742627245957127",
      "1394742420210806784"
    ],
    [
      "1394737204556046337",
      "1394620329662746627"
    ],
    [
      "1394729828893528065",
      "1394620329662746627"
    ],
    [
      "1394728501840916483",
      "1394670974545670146"
    ],
    [
      "1394728852279136266",
      "1394728501840916483"
    ],
    [
      "1394670974545670146",
      "1394669428588126210"
    ],
    [
      "1394726271771365376",
      "1394620329662746627"
    ],
    [
      "1394725210134392838",
      "1394620329662746627"
    ],
    [
      "1394724949621985282",
      "1394620329662746627"
    ],
    [
      "1394722992890994694",
      "1394620329662746627"
    ],
    [
      "1394722078004289549",
      "1394620329662746627"
    ],
    [
      "1394719053982232581",
      "1394620329662746627"
    ],
    [
      "1394717166704996354",
      "1394620329662746627"
    ],
    [
      "1394670108811751427",
      "1394668066483605511"
    ],
    [
      "1394712698911342593",
      "1394670108811751427"
    ],
    [
      "1394711148621074435",
      "1394620329662746627"
    ],
    [
      "1394710557589217282",
      "1394620329662746627"
    ],
    [
      "1394707598251864067",
      "1394620329662746627"
    ],
    [
      "1394706933202968578",
      "1394620329662746627"
    ],
    [
      "1394705953816121348",
      "1394620329662746627"
    ],
    [
      "1394671662713516033",
      "1394669933439733762"
    ],
    [
      "1394704819353538560",
      "1394671662713516033"
    ],
    [
      "1394703793799921673",
      "1394620329662746627"
    ],
    [
      "1394674381092278274",
      "1394664507587313667"
    ],
    [
      "1394703205150466051",
      "1394674381092278274"
    ],
    [
      "1394664216452210692",
      "1394639935609606157"
    ],
    [
      "1394701561088016386",
      "1394664216452210692"
    ],
    [
      "1394698408049487874",
      "1394620329662746627"
    ],
    [
      "1394696032500346881",
      "1394620329662746627"
    ],
    [
      "1394695763205165061",
      "1394620329662746627"
    ],
    [
      "1394695662323871747",
      "1394620329662746627"
    ],
    [
      "1394686404572049412",
      "1394620329662746627"
    ],
    [
      "1394693698626015232",
      "1394686404572049412"
    ],
    [
      "1394647326262808576",
      "1394627232627372033"
    ],
    [
      "1394691525951557650",
      "1394647326262808576"
    ],
    [
      "1394669428588126210",
      "1394666356482600963"
    ],
    [
      "1394691228218834946",
      "1394669428588126210"
    ],
    [
      "1394690918414966787",
      "1394620329662746627"
    ],
    [
      "1394689156564099082",
      "1394620329662746627"
    ],
    [
      "1394689119046049803",
      "1394620329662746627"
    ],
    [
      "1394687800969154560",
      "1394620329662746627"
    ],
    [
      "1394687172247130113",
      "1394620329662746627"
    ],
    [
      "1394686487384502275",
      "1394620329662746627"
    ],
    [
      "1394683197540106242",
      "1394620329662746627"
    ],
    [
      "1394682983555035138",
      "1394620329662746627"
    ],
    [
      "1394682371534901255",
      "1394660122740150274"
    ],
    [
      "1394682261577027589",
      "1394682161882669062"
    ],
    [
      "1394682367323873283",
      "1394682261577027589"
    ],
    [
      "1394682161882669062",
      "1394620329662746627"
    ],
    [
      "1394681536964923397",
      "1394620329662746627"
    ],
    [
      "1394678566055387136",
      "1394620329662746627"
    ],
    [
      "1394678496853585932",
      "1394620329662746627"
    ],
    [
      "1394678002353508354",
      "1394620329662746627"
    ],
    [
      "1394677199022837760",
      "1394620329662746627"
    ],
    [
      "1394672883918585857",
      "1394672536747663362"
    ],
    [
      "1394674919229775876",
      "1394672883918585857"
    ],
    [
      "1394664507587313667",
      "1394625607011536902"
    ],
    [
      "1394674061934923776",
      "1394672883918585857"
    ],
    [
      "1394672536747663362",
      "1394666356482600963"
    ],
    [
      "1394673424115453958",
      "1394672536747663362"
    ],
    [
      "1394673392415092743",
      "1394620329662746627"
    ],
    [
      "1394673368733937666",
      "1394620329662746627"
    ],
    [
      "1394673299448377344",
      "1394620329662746627"
    ],
    [
      "1394673060754558976",
      "1394620329662746627"
    ],
    [
      "1394672835830849539",
      "1394620329662746627"
    ],
    [
      "1394672782600978440",
      "1394620329662746627"
    ],
    [
      "1394672327007379460",
      "1394620329662746627"
    ],
    [
      "1394672767388246017",
      "1394672327007379460"
    ],
    [
      "1394642601685360646",
      "1394624048496271366"
    ],
    [
      "1394671983133003782",
      "1394642601685360646"
    ],
    [
      "1394671677674512391",
      "1394620329662746627"
    ],
    [
      "1394669933439733762",
      "1394664906478309376"
    ],
    [
      "1394670960419086337",
      "1394648172559958025"
    ],
    [
      "1394671211012136967",
      "1394670960419086337"
    ],
    [
      "1394648172559958025",
      "1394620329662746627"
    ],
    [
      "1394670791724306436",
      "1394620329662746627"
    ],
    [
      "1394670493454774285",
      "1394620329662746627"
    ],
    [
      "1394670149878308870",
      "1394620329662746627"
    ],
    [
      "1394668066483605511",
      "1394660122740150274"
    ],
    [
      "1394664906478309376",
      "1394664229333086209"
    ],
    [
      "1394668894154022918",
      "1394620329662746627"
    ],
    [
      "1394669667361476610",
      "1394668894154022918"
    ],
    [
      "1394669642262585346",
      "1394620329662746627"
    ],
    [
      "1394669544027967496",
      "1394620329662746627"
    ],
    [
      "1394668917751123973",
      "1394620329662746627"
    ],
    [
      "1394668242686382085",
      "1394620329662746627"
    ],
    [
      "1394668470743310343",
      "1394668242686382085"
    ],
    [
      "1394667944882458625",
      "1394620329662746627"
    ],
    [
      "1394646158157520896",
      "1394620329662746627"
    ],
    [
      "1394667818583400452",
      "1394646158157520896"
    ],
    [
      "1394666683974000640",
      "1394620329662746627"
    ],
    [
      "1394666681801314319",
      "1394620329662746627"
    ],
    [
      "1394666507070631938",
      "1394620329662746627"
    ],
    [
      "1394666433955704833",
      "1394647326262808576"
    ],
    [
      "1394627232627372033",
      "1394620329662746627"
    ],
    [
      "1394666410836692992",
      "1394627232627372033"
    ],
    [
      "1394665981985927174",
      "1394620329662746627"
    ],
    [
      "1394665980987682816",
      "1394620329662746627"
    ],
    [
      "1394665701739094022",
      "1394620329662746627"
    ],
    [
      "1394664229333086209",
      "1394647326262808576"
    ],
    [
      "1394625607011536902",
      "1394620329662746627"
    ],
    [
      "1394639935609606157",
      "1394620329662746627"
    ],
    [
      "1394636804394037248",
      "1394635517166297088"
    ],
    [
      "1394663068546715649",
      "1394620329662746627"
    ],
    [
      "1394647896436482048",
      "1394646158157520896"
    ],
    [
      "1394663058505715717",
      "1394647896436482048"
    ],
    [
      "1394661594102128645",
      "1394661417685508098"
    ],
    [
      "1394661536665321472",
      "1394620329662746627"
    ],
    [
      "1394661129918586886",
      "1394660122740150274"
    ],
    [
      "1394661097601372160",
      "1394620329662746627"
    ],
    [
      "1394658757779632135",
      "1394654232083681282"
    ],
    [
      "1394660515918585856",
      "1394658757779632135"
    ],
    [
      "1394660397874130944",
      "1394620329662746627"
    ],
    [
      "1394659409335181317",
      "1394620329662746627"
    ],
    [
      "1394659645789294595",
      "1394659409335181317"
    ],
    [
      "1394655727285903367",
      "1394620329662746627"
    ],
    [
      "1394659539325173760",
      "1394655727285903367"
    ],
    [
      "1394656198197235721",
      "1394620329662746627"
    ],
    [
      "1394659364003368963",
      "1394656198197235721"
    ],
    [
      "1394659194108878854",
      "1394646158157520896"
    ],
    [
      "1394659136051220482",
      "1394620329662746627"
    ],
    [
      "1394657185796263939",
      "1394620329662746627"
    ],
    [
      "1394659110071771138",
      "1394657185796263939"
    ],
    [
      "1394658798166548492",
      "1394625607011536902"
    ],
    [
      "1394654232083681282",
      "1394620329662746627"
    ],
    [
      "1394658660693934086",
      "1394657185796263939"
    ],
    [
      "1394658605735964672",
      "1394620329662746627"
    ],
    [
      "1394657591658156033",
      "1394653860250091523"
    ],
    [
      "1394658137039200259",
      "1394657591658156033"
    ],
    [
      "1394657777566601219",
      "1394657591658156033"
    ],
    [
      "1394657596221571080",
      "1394620329662746627"
    ],
    [
      "1394653860250091523",
      "1394653253061816322"
    ],
    [
      "1394656683801006086",
      "1394627232627372033"
    ],
    [
      "1394656586023542788",
      "1394620329662746627"
    ],
    [
      "1394655386133745668",
      "1394620329662746627"
    ],
    [
      "1394654736431808514",
      "1394652776584654851"
    ],
    [
      "1394654011823849473",
      "1394620329662746627"
    ],
    [
      "1394653841736536064",
      "1394620329662746627"
    ],
    [
      "1394653531731374093",
      "1394620329662746627"
    ],
    [
      "1394653384217595909",
      "1394620329662746627"
    ],
    [
      "1394638796646273025",
      "1394634868890345476"
    ],
    [
      "1394653373194903552",
      "1394638796646273025"
    ],
    [
      "1394653213052358660",
      "1394620329662746627"
    ],
    [
      "1394652622624284673",
      "1394620329662746627"
    ],
    [
      "1394652832381513731",
      "1394652622624284673"
    ],
    [
      "1394652447847731201",
      "1394620329662746627"
    ],
    [
      "1394652268205690885",
      "1394620329662746627"
    ],
    [
      "1394651061030461450",
      "1394634672408236034"
    ],
    [
      "1394651451797000193",
      "1394651061030461450"
    ],
    [
      "1394650270236299271",
      "1394648172559958025"
    ],
    [
      "1394651388609802241",
      "1394650270236299271"
    ],
    [
      "1394634672408236034",
      "1394620329662746627"
    ],
    [
      "1394651035441016834",
      "1394620329662746627"
    ],
    [
      "1394650960136339457",
      "1394620329662746627"
    ],
    [
      "1394631938498048003",
      "1394620329662746627"
    ],
    [
      "1394650544841674752",
      "1394631938498048003"
    ],
    [
      "1394648319700262914",
      "1394620329662746627"
    ],
    [
      "1394650028967403523",
      "1394648319700262914"
    ],
    [
      "1394650012513099788",
      "1394620329662746627"
    ],
    [
      "1394649921609994245",
      "1394620329662746627"
    ],
    [
      "1394648922732199944",
      "1394620329662746627"
    ],
    [
      "1394649918241972225",
      "1394648922732199944"
    ],
    [
      "1394649670337634311",
      "1394620329662746627"
    ],
    [
      "1394648115173634050",
      "1394634406812344322"
    ],
    [
      "1394648932710502400",
      "1394648115173634050"
    ],
    [
      "1394648741513109511",
      "1394620329662746627"
    ],
    [
      "1394634406812344322",
      "1394620329662746627"
    ],
    [
      "1394648051591966720",
      "1394631938498048003"
    ],
    [
      "1394648049809559553",
      "1394627232627372033"
    ],
    [
      "1394647338669510663",
      "1394620329662746627"
    ],
    [
      "1394647415513403395",
      "1394647338669510663"
    ],
    [
      "1394646364651331590",
      "1394620329662746627"
    ],
    [
      "1394646359563722754",
      "1394620329662746627"
    ],
    [
      "1394626331644661763",
      "1394625756475629574"
    ],
    [
      "1394645789146697728",
      "1394626331644661763"
    ],
    [
      "1394643320798949383",
      "1394620329662746627"
    ],
    [
      "1394642960109772801",
      "1394620329662746627"
    ],
    [
      "1394642331551375361",
      "1394620329662746627"
    ],
    [
      "1394642252396388359",
      "1394620329662746627"
    ],
    [
      "1394641188909719555",
      "1394620329662746627"
    ],
    [
      "1394640061077942279",
      "1394620329662746627"
    ],
    [
      "1394640020405952516",
      "1394620329662746627"
    ],
    [
      "1394639839463714819",
      "1394620329662746627"
    ],
    [
      "1394639819045838851",
      "1394620329662746627"
    ],
    [
      "1394639805330247685",
      "1394620329662746627"
    ],
    [
      "1394634868890345476",
      "1394620329662746627"
    ],
    [
      "1394638169619017729",
      "1394620329662746627"
    ],
    [
      "1394638100714999816",
      "1394620329662746627"
    ],
    [
      "1394637957462642690",
      "1394620329662746627"
    ],
    [
      "1394637477663547393",
      "1394634672408236034"
    ],
    [
      "1394634536055619588",
      "1394634406812344322"
    ],
    [
      "1394637466930487298",
      "1394634536055619588"
    ],
    [
      "1394637079456460805",
      "1394620329662746627"
    ],
    [
      "1394621545629327367",
      "1394620329662746627"
    ],
    [
      "1394637042257117191",
      "1394621545629327367"
    ],
    [
      "1394635517166297088",
      "1394634406812344322"
    ],
    [
      "1394636730209226752",
      "1394620329662746627"
    ],
    [
      "1394636467792658432",
      "1394620329662746627"
    ],
    [
      "1394636456119967744",
      "1394620329662746627"
    ],
    [
      "1394636175995019264",
      "1394626331644661763"
    ],
    [
      "1394636128158896131",
      "1394620329662746627"
    ],
    [
      "1394635871501144064",
      "1394634672408236034"
    ],
    [
      "1394627212217888771",
      "1394625897148338183"
    ],
    [
      "1394635018971066371",
      "1394627212217888771"
    ],
    [
      "1394634704469516288",
      "1394620329662746627"
    ],
    [
      "1394634089395855360",
      "1394620329662746627"
    ],
    [
      "1394633658246574080",
      "1394620329662746627"
    ],
    [
      "1394633263872978945",
      "1394620329662746627"
    ],
    [
      "1394633077020762115",
      "1394620329662746627"
    ],
    [
      "1394632001718833156",
      "1394620329662746627"
    ],
    [
      "1394632705841811459",
      "1394632001718833156"
    ],
    [
      "1394632615815172096",
      "1394620329662746627"
    ],
    [
      "1394632500278964224",
      "1394620329662746627"
    ],
    [
      "1394632419064549380",
      "1394620329662746627"
    ],
    [
      "1394632242245292032",
      "1394620329662746627"
    ],
    [
      "1394628221153464320",
      "1394620329662746627"
    ],
    [
      "1394632001886564354",
      "1394628221153464320"
    ],
    [
      "1394631109028335621",
      "1394620329662746627"
    ],
    [
      "1394630903222132742",
      "1394620329662746627"
    ],
    [
      "1394629716762456065",
      "1394620329662746627"
    ],
    [
      "1394630723504640000",
      "1394629716762456065"
    ],
    [
      "1394630590914256896",
      "1394620329662746627"
    ],
    [
      "1394630554117722115",
      "1394620329662746627"
    ],
    [
      "1394629829862043648",
      "1394620329662746627"
    ],
    [
      "1394629824593809415",
      "1394620329662746627"
    ],
    [
      "1394629499711594501",
      "1394620329662746627"
    ],
    [
      "1394629405159432192",
      "1394620329662746627"
    ],
    [
      "1394627494066720770",
      "1394620329662746627"
    ],
    [
      "1394627423736680448",
      "1394620329662746627"
    ],
    [
      "1394627382255001602",
      "1394620329662746627"
    ],
    [
      "1394626434501578755",
      "1394625754567225344"
    ],
    [
      "1394627374659084291",
      "1394626434501578755"
    ],
    [
      "1394625897148338183",
      "1394625607011536902"
    ],
    [
      "1394626624432263172",
      "1394620329662746627"
    ],
    [
      "1394625754567225344",
      "1394620329662746627"
    ],
    [
      "1394626425748086784",
      "1394620329662746627"
    ],
    [
      "1394625756475629574",
      "1394620329662746627"
    ],
    [
      "1394625667384422405",
      "1394620329662746627"
    ],
    [
      "1394625359996391426",
      "1394620329662746627"
    ],
    [
      "1394625080039194626",
      "1394620329662746627"
    ],
    [
      "1394624891211681797",
      "1394620329662746627"
    ],
    [
      "1394624743073013763",
      "1394620329662746627"
    ],
    [
      "1394620965900926977",
      "1394620329662746627"
    ],
    [
      "1394624452617510917",
      "1394620965900926977"
    ],
    [
      "1394624255019601921",
      "1394620329662746627"
    ],
    [
      "1394624200657326083",
      "1394621545629327367"
    ],
    [
      "1394624068998021121",
      "1394620329662746627"
    ],
    [
      "1394624025247326215",
      "1394620329662746627"
    ],
    [
      "1394623978975735810",
      "1394620329662746627"
    ],
    [
      "1394623957735776264",
      "1394620329662746627"
    ],
    [
      "1394623891679629315",
      "1394620329662746627"
    ],
    [
      "1394623545976754176",
      "1394620329662746627"
    ],
    [
      "1394623502699753475",
      "1394620329662746627"
    ],
    [
      "1394623150067945485",
      "1394620329662746627"
    ],
    [
      "1394623489211080706",
      "1394623150067945485"
    ],
    [
      "1394622641970061319",
      "1394620329662746627"
    ],
    [
      "1394622549066194952",
      "1394620329662746627"
    ],
    [
      "1394622474814377986",
      "1394620329662746627"
    ],
    [
      "1394622205485633536",
      "1394620329662746627"
    ],
    [
      "1394621809430089729",
      "1394620329662746627"
    ],
    [
      "1394621003662249987",
      "1394620329662746627"
    ]
  ]
}