{
  "nodes": [
    {
      "id": "1269401667612491776",
      "url": "https://twitter.com/danilitos/status/1269401667612491776",
      "user": "danilitos",
      "text": "@_TheCivilRight The 8 years with good behavior reduced to 5, and with jail overcrowding down to 3, and with discretionary parole down to 1 1/2, and with timed served he will be out before you know it.",
      "sentiment": 0.4404
    },
    {
      "id": "1269400147365990400",
      "url": "https://twitter.com/danilitos/status/1269400147365990400",
      "user": "danilitos",
      "text": "@Coastline_CEO @_TheCivilRight ...and they will, unfortunately",
      "sentiment": -0.34
    },
    {
      "id": "1269387380781395969",
      "url": "https://twitter.com/Huskersp/status/1269387380781395969",
      "user": "Huskersp",
      "text": "@_TheCivilRight @UncleHotep 8 years? Should be 28 life sentences!!",
      "sentiment": 0.1984
    },
    {
      "id": "1269356864053170181",
      "url": "https://twitter.com/whittravis69/status/1269356864053170181",
      "user": "whittravis69",
      "text": "@CliffMohler @_TheCivilRight I get it. \\n...and aside from this dude, you're right. For profit prisons and especially the school to prison pipeline is what I believe to be the 3rd biggest issue effecting inner city especially Black communities",
      "sentiment": -0.1027
    },
    {
      "id": "1269377038659588098",
      "url": "https://twitter.com/CliffMohler/status/1269377038659588098",
      "user": "CliffMohler",
      "text": "@Parker54Ed @_TheCivilRight Definitely. That pipeline is a problem for everyone, but blacks seem to be disproportionately represented in those figures. The black community has some serious issues that need addressed, and every one of them seems to be intertwined.",
      "sentiment": -0.1154
    },
    {
      "id": "1269364872392740864",
      "url": "https://twitter.com/blade329/status/1269364872392740864",
      "user": "blade329",
      "text": "@_TheCivilRight @UncleHotep That\u2019s not a man, it\u2019s a thing.",
      "sentiment": 0.0
    },
    {
      "id": "1269354987265626115",
      "url": "https://twitter.com/CliffMohler/status/1269354987265626115",
      "user": "CliffMohler",
      "text": "@Parker54Ed @_TheCivilRight I see where my comment could be taken wrong though. That's my bad.",
      "sentiment": -0.765
    },
    {
      "id": "1269354553696280578",
      "url": "https://twitter.com/CliffMohler/status/1269354553696280578",
      "user": "CliffMohler",
      "text": "@Parker54Ed @_TheCivilRight That's not at all what I said dude. That fucker needs to die. I meant that a weed charge is a petty charge. What dude did deserves public execution.",
      "sentiment": -0.875
    },
    {
      "id": "1269355338777726976",
      "url": "https://twitter.com/CliffMohler/status/1269355338777726976",
      "user": "CliffMohler",
      "text": "@Parker54Ed @_TheCivilRight This was my suggestion in another comment, lol. https://t.co/00oNWqCtTV",
      "sentiment": 0.4215
    },
    {
      "id": "1269354682897633287",
      "url": "https://twitter.com/GunplabroYT/status/1269354682897633287",
      "user": "GunplabroYT",
      "text": "@_TheCivilRight @crapc0rno At the very least that dude should be locked up for life.",
      "sentiment": 0.0
    },
    {
      "id": "1269353814198554625",
      "url": "https://twitter.com/whittravis69/status/1269353814198554625",
      "user": "whittravis69",
      "text": "@CliffMohler @_TheCivilRight Hmm, I thought you would have circled back to \"clarify\" that you think a dude that molested 28 kids is NOT a \"petty offender\" https://t.co/1QoFiEAV3S",
      "sentiment": -0.0511
    },
    {
      "id": "1269351195967176705",
      "url": "https://twitter.com/CliffMohler/status/1269351195967176705",
      "user": "CliffMohler",
      "text": "@Parker54Ed @_TheCivilRight Let me clarify. I'm not saying that his skin tone didn't play a part, but we see this all the time. Dude will kill someone and get 15. Next dude sells a dime bag of weed and catches 25. Shit doesn't add up.",
      "sentiment": -0.9321
    },
    {
      "id": "1269347754750459908",
      "url": "https://twitter.com/whittravis69/status/1269347754750459908",
      "user": "whittravis69",
      "text": "@_TheCivilRight \"8 years for molesting 28 kids\" https://t.co/tFULe2sWAr",
      "sentiment": -0.5859
    },
    {
      "id": "1269350768953491456",
      "url": "https://twitter.com/CliffMohler/status/1269350768953491456",
      "user": "CliffMohler",
      "text": "@Parker54Ed @_TheCivilRight Is it though? Or is it a fucked up justice system that sees more money in locking up petty offenders? Not saying that blacks don't catch more severe sentences for some of the same shit. The DoJ damned sure likes doing that.. Just saying that it's bigger than just one issue.",
      "sentiment": -0.5968
    },
    {
      "id": "1269349610079780865",
      "url": "https://twitter.com/CliffMohler/status/1269349610079780865",
      "user": "CliffMohler",
      "text": "@_TheCivilRight @UncleHotep Murder? Nah. Tie him up, bent over a stump, spray him with cow sex pheromones, and turn a bull loose on him. Rinse and repeat until he's dead. Sounds fair to me, anyway.\ud83e\udd37\u200d\u2642\ufe0f",
      "sentiment": -0.886
    },
    {
      "id": "1269349291103064066",
      "url": "https://twitter.com/jakeisacrazy1/status/1269349291103064066",
      "user": "jakeisacrazy1",
      "text": "@_TheCivilRight @UncleHotep Meanwhile, #BLM wants to #DefundThePolice. Brilliant plan... But mob justice might be good for pedophiles, eh?",
      "sentiment": 0.8968
    },
    {
      "id": "1269345054184873985",
      "url": "https://twitter.com/4everxgrateful/status/1269345054184873985",
      "user": "4everxgrateful",
      "text": "@_TheCivilRight 8 years that\u2019s it?",
      "sentiment": 0.0
    }
  ],
  "edges": [
    [
      "1269401667612491776",
      "1269342397927915521"
    ],
    [
      "1269400147365990400",
      "1269386029418586117"
    ],
    [
      "1269387380781395969",
      "1269342397927915521"
    ],
    [
      "1269356864053170181",
      "1269354987265626115"
    ],
    [
      "1269377038659588098",
      "1269356864053170181"
    ],
    [
      "1269364872392740864",
      "1269342397927915521"
    ],
    [
      "1269354987265626115",
      "1269354553696280578"
    ],
    [
      "1269354553696280578",
      "1269353814198554625"
    ],
    [
      "1269355338777726976",
      "1269354553696280578"
    ],
    [
      "1269354682897633287",
      "1269342397927915521"
    ],
    [
      "1269353814198554625",
      "1269351195967176705"
    ],
    [
      "1269351195967176705",
      "1269347754750459908"
    ],
    [
      "1269347754750459908",
      "1269342397927915521"
    ],
    [
      "1269350768953491456",
      "1269347754750459908"
    ],
    [
      "1269349610079780865",
      "1269342397927915521"
    ],
    [
      "1269349291103064066",
      "1269342397927915521"
    ],
    [
      "1269345054184873985",
      "1269342397927915521"
    ]
  ]
}